pyDSA_core/YL_fitting.py
pyDSA_core/__init__.py
pyDSA_core/baseline.py
pyDSA_core/dropedges.py
pyDSA_core/dropfit.py
pyDSA_core/helpers.py
pyDSA_core/image.py
pyDSA_core/temporaldropedges.py
pyDSA_core/temporalfits.py
pyDSA_core/temporalimages.py
pyDSA_core-1.4.1.dist-info/LICENSE
pyDSA_core-1.4.1.dist-info/METADATA
pyDSA_core-1.4.1.dist-info/WHEEL
pyDSA_core-1.4.1.dist-info/top_level.txt
pyDSA_core-1.4.1.dist-info/RECORD
