Metadata-Version: 2.1
Name: pyDSA_core
Version: 1.4.1
Summary: Python Drop Shape Analyzer
Home-page: https://framagit.org/gabylaunay/pyDSA_core
Author: Gaby Launay
Author-email: gaby.launay@protonmail.com
Keywords: DSA drop shape contact angle hysteresis
Classifier: Development Status :: 5 - Production/Stable
Classifier: Intended Audience :: Science/Research
Classifier: Topic :: Scientific/Engineering
Classifier: Programming Language :: Python :: 3.5
Classifier: Natural Language :: English
Classifier: License :: OSI Approved :: GNU General Public License v3 (GPLv3)
Classifier: Operating System :: POSIX :: Linux
License-File: LICENSE
Requires-Dist: numpy
Requires-Dist: matplotlib
Requires-Dist: opencv-python-headless
Requires-Dist: scipy
Requires-Dist: imageio
Requires-Dist: scikit-image
Requires-Dist: IMTreatment >=1.3.5
